dubna_parser/__init__.py
dubna_parser/consts.py
dubna_parser/downloader.py
dubna_parser/enums.py
dubna_parser/models.py
dubna_parser/parser.py
dubna_parser/utils.py
dubna_parser-0.1.0.dist-info/METADATA
dubna_parser-0.1.0.dist-info/WHEEL
dubna_parser-0.1.0.dist-info/RECORD
