Metadata-Version: 2.1
Name: dubna-parser
Version: 0.1.0
Summary: package for parsing schedule of Dubna
Author: Skelesheit
Author-email: Skelesheit@gmail.com
Requires-Python: >=3.12,<4.0
Classifier: Programming Language :: Python :: 3
Classifier: Programming Language :: Python :: 3.12
Requires-Dist: gdown (>=5.2.0,<6.0.0)
Requires-Dist: openpyxl (>=3.1.5,<4.0.0)
